rdrpcatch/__init__.py
rdrpcatch/rdrpcatch_wrapper.py
rdrpcatch/cli/__init__.py
rdrpcatch/cli/args.py
rdrpcatch/rdrpcatch_scripts/__init__.py
rdrpcatch/rdrpcatch_scripts/fetch_dbs.py
rdrpcatch/rdrpcatch_scripts/format_pyhmmer_out.py
rdrpcatch/rdrpcatch_scripts/gui.py
rdrpcatch/rdrpcatch_scripts/mmseqs_tax.py
rdrpcatch/rdrpcatch_scripts/paths.py
rdrpcatch/rdrpcatch_scripts/plot.py
rdrpcatch/rdrpcatch_scripts/run_pyhmmer.py
rdrpcatch/rdrpcatch_scripts/run_seqkit.py
rdrpcatch/rdrpcatch_scripts/utils.py
rdrpcatch-0.0.8.dist-info/METADATA
rdrpcatch-0.0.8.dist-info/WHEEL
rdrpcatch-0.0.8.dist-info/entry_points.txt
rdrpcatch-0.0.8.dist-info/licenses/LICENSE
rdrpcatch-0.0.8.dist-info/RECORD
