Metadata-Version: 2.4
Name: rdrpcatch
Version: 0.0.8
Dynamic: Summary
Project-URL: Home, https://github.com/dimitris-karapliafis/RdRpCATCH
Project-URL: Source, https://github.com/dimitris-karapliafis/RdRpCATCH
Author-email: Dimitris Karapliafis <dimitris.karapliafis@wur.nl>, Uri Neri <uneri@lbl.gov>, RdRpCATCH contributors <dimitris.karapliafis@wur.nl>
License: MIT
License-File: LICENSE
Requires-Python: >=3.12
Requires-Dist: altair==5.5.0
Requires-Dist: matplotlib==3.10.1
Requires-Dist: needletail==0.6.3
Requires-Dist: pandas==2.2.3
Requires-Dist: polars==1.26.0
Requires-Dist: pyhmmer==0.11.0
Requires-Dist: requests==2.32.3
Requires-Dist: rich-click==1.8.8
Requires-Dist: rich==13.9.4
Requires-Dist: upsetplot==0.9.0
